loss_landscapes/__init__.py
loss_landscapes/connecting_paths.py
loss_landscapes/landscapes.py
loss_landscapes/main.py
loss_landscapes/saddle_points.py
loss_landscapes/trajectories.py
loss_landscapes/common/__init__.py
loss_landscapes/common/evaluators/__init__.py
loss_landscapes/common/evaluators/evaluators.py
loss_landscapes/common/evaluators/torch/__init__.py
loss_landscapes/common/evaluators/torch/misc_evaluators.py
loss_landscapes/common/evaluators/torch/rl_evaluators.py
loss_landscapes/common/evaluators/torch/sl_evaluators.py
loss_landscapes/common/model_interface/__init__.py
loss_landscapes/common/model_interface/agent_interface.py
loss_landscapes/common/model_interface/model_tensor.py
loss_landscapes/common/model_interface/model_vector.py
loss_landscapes/common/model_interface/model_wrapper.py
loss_landscapes/common/model_interface/tensor_factory.py
loss_landscapes/common/model_interface/wrapper_factory.py
loss_landscapes/common/model_interface/torch/__init__.py
loss_landscapes/common/model_interface/torch/torch_tensor.py
loss_landscapes/common/model_interface/torch/torch_vector.py
loss_landscapes/common/model_interface/torch/torch_wrappers.py
loss_landscapes/connecting_paths/__init__.py
loss_landscapes/connecting_paths/connecting_paths.py
loss_landscapes/contrib/__init__.py
loss_landscapes/contrib/connecting_paths.py
loss_landscapes/contrib/trajectories.py
loss_landscapes/entities/__init__.py
loss_landscapes/entities/parametric_curve.py
loss_landscapes/evaluators/__init__.py
loss_landscapes/evaluators/evaluator.py
loss_landscapes/evaluators/evaluators.py
loss_landscapes/evaluators/torch/__init__.py
loss_landscapes/evaluators/torch/loss_evaluators.py
loss_landscapes/evaluators/torch/metric_evaluators.py
loss_landscapes/evaluators/torch/misc_evaluators.py
loss_landscapes/evaluators/torch/rl_evaluators.py
loss_landscapes/evaluators/torch/sl_evaluators.py
loss_landscapes/metrics/__init__.py
loss_landscapes/metrics/metric.py
loss_landscapes/metrics/rl_metrics.py
loss_landscapes-3.0.6.dist-info/METADATA
loss_landscapes-3.0.6.dist-info/WHEEL
loss_landscapes-3.0.6.dist-info/top_level.txt
loss_landscapes-3.0.6.dist-info/RECORD
