Metadata-Version: 2.1
Name: loss-landscapes
Version: 3.0.6
Summary: A library for approximating loss landscapes in low-dimensional parameter subspaces
Home-page: https://github.com/marcellodebernardi/loss-landscapes
Author: Marcello De Bernardi
Author-email: marcello.debernardi@stcatz.ox.ac.uk
License: MIT
Platform: UNKNOWN
Classifier: Development Status :: 4 - Beta
Classifier: Intended Audience :: Developers
Classifier: Topic :: Scientific/Engineering :: Artificial Intelligence
Classifier: License :: OSI Approved :: MIT License
Classifier: Programming Language :: Python :: 3.5
Classifier: Programming Language :: Python :: 3.6
Classifier: Programming Language :: Python :: 3.7
Requires-Python: >=3.5
Requires-Dist: numpy
